arpifs_listings/TLAD.py
arpifs_listings/__init__.py
arpifs_listings/cost_functions.py
arpifs_listings/jo_tables.py
arpifs_listings/listings.py
arpifs_listings/norms.py
arpifs_listings/util.py
arpifs_listings/entrypoints/__init__.py
arpifs_listings/entrypoints/compare_listings.py
arpifs_listings-1.2.2.dist-info/licenses/LICENSE-en.txt
arpifs_listings-1.2.2.dist-info/licenses/LICENSE.txt
arpifs_listings-1.2.2.dist-info/METADATA
arpifs_listings-1.2.2.dist-info/WHEEL
arpifs_listings-1.2.2.dist-info/entry_points.txt
arpifs_listings-1.2.2.dist-info/top_level.txt
arpifs_listings-1.2.2.dist-info/RECORD
