Metadata-Version: 2.4
Name: arpifs_listings
Version: 1.2.2
Summary: Processing and comparison of various data from Arpege/IFS listings.
Author-email: The Vortex Team <vortex.support@meteo.fr>
License: CECILL-C
Project-URL: repository, https://github.com/UMR-CNRM/arpifs_listings
Classifier: Development Status :: 4 - Beta
Classifier: License :: CeCILL-C Free Software License Agreement (CECILL-C)
Requires-Python: >=3.7
License-File: LICENSE-en.txt
License-File: LICENSE.txt
Requires-Dist: bronx
Provides-Extra: docs
Requires-Dist: sphinx; extra == "docs"
Provides-Extra: graphics
Requires-Dist: matplotlib; extra == "graphics"
Dynamic: license-file
